{
    "condition": "minecraft:any_of",
    "terms": [
        {
            "condition": "minecraft:reference",
            "name": "eoflib:inventory/offhand/offhand_empty"
        },
        {
            "condition": "minecraft:inverted",
            "term": {
                "condition": "minecraft:any_of",
                "terms": [
                    {
                        "condition": "minecraft:reference",
                        "name": "eoflib:inventory/offhand/offhand_empty"
                    },
                    {
                        "condition": "minecraft:entity_properties",
                        "entity": "this",
                        "predicate": {
                            "nbt": "{Inventory: [{Slot: -106b, components: {\"minecraft:custom_data\": {\"eof_data\": {\"ability_data\": {\"archetype\": \"tertiary\"}}}}}]}"
                        }
                    }
                ]
            }
        }
    ]
}
